{
  "totales": {
    "PorcentajeDesaparecidos": "31.10",
    "PorcentajeLocalizados": "68.90",
    "PorcentajeLocalizadosCV": "91.00",
    "PorcentajeLocalizadosSV": "9.00",
    "PorcentajeSoloDesaparecidos": "91.46",
    "PorcentajeSoloNoLocalizados": "8.54",
    "TotalDesaparecidos": "316",
    "TotalGlobal": "1016",
    "TotalLocalizados": "700",
    "TotalLocalizadosCV": "637",
    "TotalLocalizadosSV": "63",
    "TotalSoloDesaparecidos": "289",
    "TotalSoloNoLocalizados": "27"
  },
  "espacial": {
    "Hombres": {
      "5 DE MAYO": 2,
      "AMPLIACIÓN 5 DE MAYO": 1,
      "AMPLIACIÓN ESMERALDA": 1,
      "AMPLIACIÓN OZUMBILLA": 2,
      "ATLAUTENCO": 1,
      "EJIDO DE TECAMAC": 1,
      "ESMERALDA": 1,
      "HUEYOTENCO": 2,
      "ISIDRO FABELA": 0,
      "LOMA BONITA": 5,
      "LOMAS DE OZUMBILLA": 1,
      "LOMAS DE SAN PEDRO ATZOMPA": 1,
      "LOMAS DE TECAMAC": 26,
      "LOS HÉROES TECAMAC I": 29,
      "LOS HÉROES TECAMAC II": 14,
      "LOS OLIVOS": 3,
      "LOS REYES ACOZAC": 5,
      "NOPALERA": 0,
      "NUEVA SANTA MARÍA (DE SAN PABLO TECALCO)": 2,
      "OJO DE AGUA": 8,
      "PORTAL OJO DE AGUA": 0,
      "REAL DEL SOL": 0,
      "SAN ANTONIO": 0,
      "SAN FRANCISCO CUAUTLIQUIXCA": 1,
      "SAN JERÓNIMO XONACAHUACAN": 4,
      "SAN LUCAS XOLOX": 2,
      "SAN MARTÍN AZCATEPEC": 4,
      "SAN MATEO TECALCO": 1,
      "SAN PABLO TECALCO": 3,
      "SAN PEDRO ATZOMPA": 4,
      "SAN PEDRO POTZOHUACAN": 4,
      "SANTA CRUZ": 5,
      "SANTA MARÍA AJOLOAPAN": 3,
      "SANTA MARÍA OZUMBILLA": 2,
      "SANTO DOMINGO AJOLOAPAN": 1,
      "SIERRA HERMOSA": 3,
      "SIN COLONIA DE REFERENCIA": 377,
      "TECÁMAC DE FELIPE VILLANUEVA CENTRO": 6,
      "VILLAS DEL REAL": 4
    },
    "Indeterminado": {
      "5 DE MAYO": 0,
      "AMPLIACIÓN 5 DE MAYO": 0,
      "AMPLIACIÓN ESMERALDA": 0,
      "AMPLIACIÓN OZUMBILLA": 0,
      "ATLAUTENCO": 0,
      "EJIDO DE TECAMAC": 0,
      "ESMERALDA": 0,
      "HUEYOTENCO": 0,
      "ISIDRO FABELA": 0,
      "LOMA BONITA": 0,
      "LOMAS DE OZUMBILLA": 0,
      "LOMAS DE SAN PEDRO ATZOMPA": 0,
      "LOMAS DE TECAMAC": 0,
      "LOS HÉROES TECAMAC I": 0,
      "LOS HÉROES TECAMAC II": 0,
      "LOS OLIVOS": 0,
      "LOS REYES ACOZAC": 0,
      "NOPALERA": 0,
      "NUEVA SANTA MARÍA (DE SAN PABLO TECALCO)": 0,
      "OJO DE AGUA": 0,
      "PORTAL OJO DE AGUA": 0,
      "REAL DEL SOL": 0,
      "SAN ANTONIO": 0,
      "SAN FRANCISCO CUAUTLIQUIXCA": 0,
      "SAN JERÓNIMO XONACAHUACAN": 0,
      "SAN LUCAS XOLOX": 0,
      "SAN MARTÍN AZCATEPEC": 0,
      "SAN MATEO TECALCO": 0,
      "SAN PABLO TECALCO": 0,
      "SAN PEDRO ATZOMPA": 0,
      "SAN PEDRO POTZOHUACAN": 0,
      "SANTA CRUZ": 0,
      "SANTA MARÍA AJOLOAPAN": 0,
      "SANTA MARÍA OZUMBILLA": 0,
      "SANTO DOMINGO AJOLOAPAN": 0,
      "SIERRA HERMOSA": 0,
      "SIN COLONIA DE REFERENCIA": 0,
      "TECÁMAC DE FELIPE VILLANUEVA CENTRO": 0,
      "VILLAS DEL REAL": 0
    },
    "Mujeres": {
      "5 DE MAYO": 1,
      "AMPLIACIÓN 5 DE MAYO": 0,
      "AMPLIACIÓN ESMERALDA": 0,
      "AMPLIACIÓN OZUMBILLA": 1,
      "ATLAUTENCO": 0,
      "EJIDO DE TECAMAC": 1,
      "ESMERALDA": 1,
      "HUEYOTENCO": 1,
      "ISIDRO FABELA": 2,
      "LOMA BONITA": 6,
      "LOMAS DE OZUMBILLA": 2,
      "LOMAS DE SAN PEDRO ATZOMPA": 0,
      "LOMAS DE TECAMAC": 9,
      "LOS HÉROES TECAMAC I": 22,
      "LOS HÉROES TECAMAC II": 3,
      "LOS OLIVOS": 1,
      "LOS REYES ACOZAC": 7,
      "NOPALERA": 1,
      "NUEVA SANTA MARÍA (DE SAN PABLO TECALCO)": 0,
      "OJO DE AGUA": 8,
      "PORTAL OJO DE AGUA": 1,
      "REAL DEL SOL": 1,
      "SAN ANTONIO": 1,
      "SAN FRANCISCO CUAUTLIQUIXCA": 1,
      "SAN JERÓNIMO XONACAHUACAN": 1,
      "SAN LUCAS XOLOX": 3,
      "SAN MARTÍN AZCATEPEC": 6,
      "SAN MATEO TECALCO": 3,
      "SAN PABLO TECALCO": 1,
      "SAN PEDRO ATZOMPA": 6,
      "SAN PEDRO POTZOHUACAN": 5,
      "SANTA CRUZ": 4,
      "SANTA MARÍA AJOLOAPAN": 0,
      "SANTA MARÍA OZUMBILLA": 1,
      "SANTO DOMINGO AJOLOAPAN": 2,
      "SIERRA HERMOSA": 4,
      "SIN COLONIA DE REFERENCIA": 368,
      "TECÁMAC DE FELIPE VILLANUEVA CENTRO": 3,
      "VILLAS DEL REAL": 10
    }
  },
  "anual": {
    "Hombre": {
      "1.CIFRA SIN  AÑO DE REFERENCIA": 75,
      "1976": 0,
      "1995": 1,
      "2000": 0,
      "2004": 1,
      "2007": 4,
      "2008": 2,
      "2009": 3,
      "2010": 0,
      "2011": 5,
      "2012": 10,
      "2013": 17,
      "2014": 8,
      "2015": 16,
      "2016": 24,
      "2017": 29,
      "2018": 10,
      "2019": 10,
      "2020": 51,
      "2021": 64,
      "2022": 53,
      "2023": 95,
      "2024": 51
    },
    "Indeterminado": {
      "1.CIFRA SIN  AÑO DE REFERENCIA": 0,
      "1976": 0,
      "1995": 0,
      "2000": 0,
      "2004": 0,
      "2007": 0,
      "2008": 0,
      "2009": 0,
      "2010": 0,
      "2011": 0,
      "2012": 0,
      "2013": 0,
      "2014": 0,
      "2015": 0,
      "2016": 0,
      "2017": 0,
      "2018": 0,
      "2019": 0,
      "2020": 0,
      "2021": 0,
      "2022": 0,
      "2023": 0,
      "2024": 0
    },
    "Mujer": {
      "1.CIFRA SIN  AÑO DE REFERENCIA": 70,
      "1976": 1,
      "1995": 0,
      "2000": 1,
      "2004": 0,
      "2007": 0,
      "2008": 0,
      "2009": 0,
      "2010": 1,
      "2011": 5,
      "2012": 3,
      "2013": 12,
      "2014": 4,
      "2015": 25,
      "2016": 32,
      "2017": 31,
      "2018": 15,
      "2019": 14,
      "2020": 62,
      "2021": 76,
      "2022": 22,
      "2023": 64,
      "2024": 49
    }
  },
  "mensual_ultimo_anio": {
    "Hombre": {
      "2023-AGOSTO": 8,
      "2023-DICIEMBRE": 6,
      "2023-NOVIEMBRE": 10,
      "2023-OCTUBRE": 8,
      "2023-SEPTIEMBRE": 14,
      "2024-ABRIL": 10,
      "2024-ENERO": 5,
      "2024-FEBRERO": 5,
      "2024-JULIO": 3,
      "2024-JUNIO": 8,
      "2024-MARZO": 10,
      "2024-MAYO": 10
    },
    "Indeterminado": {
      "2023-AGOSTO": 0,
      "2023-DICIEMBRE": 0,
      "2023-NOVIEMBRE": 0,
      "2023-OCTUBRE": 0,
      "2023-SEPTIEMBRE": 0,
      "2024-ABRIL": 0,
      "2024-ENERO": 0,
      "2024-FEBRERO": 0,
      "2024-JULIO": 0,
      "2024-JUNIO": 0,
      "2024-MARZO": 0,
      "2024-MAYO": 0
    },
    "Mujer": {
      "2023-AGOSTO": 2,
      "2023-DICIEMBRE": 3,
      "2023-NOVIEMBRE": 6,
      "2023-OCTUBRE": 4,
      "2023-SEPTIEMBRE": 7,
      "2024-ABRIL": 11,
      "2024-ENERO": 7,
      "2024-FEBRERO": 8,
      "2024-JULIO": 2,
      "2024-JUNIO": 4,
      "2024-MARZO": 9,
      "2024-MAYO": 8
    }
  },
  "por_edad": {
    "Hombres": {
      "0": 2,
      "1": 5,
      "10": 7,
      "11": 3,
      "12": 9,
      "123": 1,
      "13": 11,
      "14": 16,
      "15": 15,
      "16": 23,
      "17": 11,
      "18": 6,
      "19": 11,
      "2": 3,
      "20": 8,
      "21": 13,
      "22": 15,
      "23": 11,
      "24": 12,
      "25": 3,
      "26": 11,
      "27": 14,
      "28": 7,
      "29": 12,
      "3": 1,
      "30": 7,
      "31": 7,
      "32": 19,
      "33": 7,
      "34": 13,
      "35": 11,
      "36": 5,
      "37": 6,
      "38": 3,
      "39": 4,
      "4": 1,
      "40": 6,
      "41": 8,
      "42": 10,
      "43": 3,
      "44": 3,
      "45": 8,
      "46": 4,
      "47": 3,
      "48": 8,
      "49": 8,
      "5": 7,
      "50": 7,
      "51": 5,
      "52": 4,
      "53": 1,
      "54": 2,
      "55": 6,
      "56": 6,
      "57": 2,
      "58": 3,
      "59": 4,
      "6": 3,
      "60": 2,
      "61": 2,
      "62": 1,
      "63": 0,
      "64": 2,
      "65": 3,
      "66": 1,
      "67": 2,
      "68": 0,
      "7": 6,
      "70": 3,
      "71": 2,
      "73": 1,
      "74": 1,
      "75": 2,
      "76": 1,
      "78": 3,
      "79": 2,
      "8": 8,
      "80": 2,
      "81": 2,
      "83": 1,
      "84": 2,
      "87": 1,
      "9": 4,
      "91": 1,
      "93": 0,
      "SIN EDAD DE REFERENCIA": 50
    },
    "Indeterminado": {
      "0": 0,
      "1": 0,
      "10": 0,
      "11": 0,
      "12": 0,
      "123": 0,
      "13": 0,
      "14": 0,
      "15": 0,
      "16": 0,
      "17": 0,
      "18": 0,
      "19": 0,
      "2": 0,
      "20": 0,
      "21": 0,
      "22": 0,
      "23": 0,
      "24": 0,
      "25": 0,
      "26": 0,
      "27": 0,
      "28": 0,
      "29": 0,
      "3": 0,
      "30": 0,
      "31": 0,
      "32": 0,
      "33": 0,
      "34": 0,
      "35": 0,
      "36": 0,
      "37": 0,
      "38": 0,
      "39": 0,
      "4": 0,
      "40": 0,
      "41": 0,
      "42": 0,
      "43": 0,
      "44": 0,
      "45": 0,
      "46": 0,
      "47": 0,
      "48": 0,
      "49": 0,
      "5": 0,
      "50": 0,
      "51": 0,
      "52": 0,
      "53": 0,
      "54": 0,
      "55": 0,
      "56": 0,
      "57": 0,
      "58": 0,
      "59": 0,
      "6": 0,
      "60": 0,
      "61": 0,
      "62": 0,
      "63": 0,
      "64": 0,
      "65": 0,
      "66": 0,
      "67": 0,
      "68": 0,
      "7": 0,
      "70": 0,
      "71": 0,
      "73": 0,
      "74": 0,
      "75": 0,
      "76": 0,
      "78": 0,
      "79": 0,
      "8": 0,
      "80": 0,
      "81": 0,
      "83": 0,
      "84": 0,
      "87": 0,
      "9": 0,
      "91": 0,
      "93": 0,
      "SIN EDAD DE REFERENCIA": 0
    },
    "Mujeres": {
      "0": 4,
      "1": 2,
      "10": 5,
      "11": 7,
      "12": 12,
      "123": 0,
      "13": 26,
      "14": 34,
      "15": 43,
      "16": 49,
      "17": 22,
      "18": 23,
      "19": 11,
      "2": 2,
      "20": 17,
      "21": 10,
      "22": 7,
      "23": 2,
      "24": 9,
      "25": 8,
      "26": 4,
      "27": 3,
      "28": 8,
      "29": 8,
      "3": 6,
      "30": 13,
      "31": 3,
      "32": 5,
      "33": 5,
      "34": 5,
      "35": 1,
      "36": 4,
      "37": 3,
      "38": 4,
      "39": 4,
      "4": 3,
      "40": 3,
      "41": 2,
      "42": 1,
      "43": 3,
      "44": 0,
      "45": 1,
      "46": 1,
      "47": 2,
      "48": 1,
      "49": 4,
      "5": 8,
      "50": 3,
      "51": 2,
      "52": 0,
      "53": 1,
      "54": 3,
      "55": 0,
      "56": 0,
      "57": 0,
      "58": 1,
      "59": 1,
      "6": 3,
      "60": 2,
      "61": 0,
      "62": 1,
      "63": 2,
      "64": 2,
      "65": 3,
      "66": 1,
      "67": 0,
      "68": 1,
      "7": 4,
      "70": 0,
      "71": 0,
      "73": 0,
      "74": 1,
      "75": 1,
      "76": 1,
      "78": 0,
      "79": 0,
      "8": 4,
      "80": 1,
      "81": 0,
      "83": 0,
      "84": 0,
      "87": 0,
      "9": 6,
      "91": 0,
      "93": 1,
      "SIN EDAD DE REFERENCIA": 44
    }
  },
  "por_nacionalidad": {
    "Hombres": {
      "COLOMBIANA": 0,
      "ESTADOUNIDENSE": 1,
      "LEICHTENSTEIN": 1,
      "MEXICANA": 525,
      "SE DESCONOCE": 0,
      "VENEZOLANA": 2
    },
    "Indeterminado": {
      "COLOMBIANA": 0,
      "ESTADOUNIDENSE": 0,
      "LEICHTENSTEIN": 0,
      "MEXICANA": 0,
      "SE DESCONOCE": 0,
      "VENEZOLANA": 0
    },
    "Mujeres": {
      "COLOMBIANA": 2,
      "ESTADOUNIDENSE": 0,
      "LEICHTENSTEIN": 0,
      "MEXICANA": 481,
      "SE DESCONOCE": 3,
      "VENEZOLANA": 1
    }
  },
  "parametros": {
    "titulo": "PERSONAS DESAPARECIDAS, NO LOCALIZADAS Y LOCALIZADAS",
    "id_estatus_victima": "0",
    "fecha_inicio": "",
    "fecha_fin": "",
    "id_estado": "15",
    "id_municipio": "81",
    "mostrar_fecha_nula": "0",
    "id_colonia": "0",
    "id_nacionalidad": "0",
    "edad_inicio": "",
    "edad_fin": "",
    "mostrar_edad_nula": "0",
    "id_hipotesis": "",
    "id_medio_conocimiento": "",
    "id_circunstancia": "",
    "tiene_discapacidad": "",
    "id_tipo_discapacidad": "0",
    "id_etnia": "0",
    "id_lengua": "0",
    "id_religion": "",
    "es_migrante": "",
    "id_estatus_migratorio": "0",
    "es_lgbttti": "",
    "es_servidor_publico": "",
    "es_defensor_dh": "",
    "es_periodista": "",
    "es_sindicalista": "",
    "es_ong": "",
    "id_hipotesis_no_localizacion": "0",
    "id_delito": "0"
  }
}