{
  "totales": {
    "PorcentajeDesaparecidos": "17.16",
    "PorcentajeLocalizados": "82.84",
    "PorcentajeLocalizadosCV": "92.23",
    "PorcentajeLocalizadosSV": "7.77",
    "PorcentajeSoloDesaparecidos": "67.19",
    "PorcentajeSoloNoLocalizados": "32.81",
    "TotalDesaparecidos": "64",
    "TotalGlobal": "373",
    "TotalLocalizados": "309",
    "TotalLocalizadosCV": "285",
    "TotalLocalizadosSV": "24",
    "TotalSoloDesaparecidos": "43",
    "TotalSoloNoLocalizados": "21"
  },
  "espacial": {
    "Hombres": {
      "ARCILA": 1,
      "BANTHI": 1,
      "BENITO JUÁREZ": 2,
      "BOSQUES DE BANTHI": 0,
      "CERRO GORDO": 0,
      "COMERI BANTHI": 0,
      "DEPORTIVA": 1,
      "DOLORES CUADRILLA DE ENMEDIO": 0,
      "DOLORES GODOY": 1,
      "EL CAZADERO": 1,
      "EL COTO": 2,
      "EL JAZMÍN": 1,
      "EL MARFIL": 1,
      "EL MIRADOR": 1,
      "EL PEDREGAL": 1,
      "EL PEDREGOSO INFONAVIT": 1,
      "GRANJAS BANTHI": 4,
      "JARDINES BANTHI": 1,
      "LA CRUZ": 1,
      "LA ESTANCIA": 0,
      "LA FLORESTA I": 1,
      "LA LLAVE": 1,
      "LA PEÑA": 1,
      "LA VALLA": 2,
      "LAS PALOMAS": 1,
      "LAS ÁGUILAS": 0,
      "LOMA LINDA": 1,
      "LOMAS DE SAN JUAN": 1,
      "LOMAS DEL PEDREGAL": 0,
      "LOS NOGALES": 1,
      "LOS OLIVOS": 1,
      "NUEVO SAN ISIDRO": 1,
      "NUEVO SAN JUAN": 3,
      "PALMA DE ROMERO": 0,
      "PALMILLAS": 3,
      "PASO DE MATA": 3,
      "PEDREGOSO COMEVI INDECO": 2,
      "PUERTA DE PALMILLAS": 3,
      "QUINTAS DE GUADALUPE": 0,
      "RANCHO BANTHI": 2,
      "RANCHO DE ENMEDIO": 1,
      "SABINO CHICO": 0,
      "SAGRADO CORAZÓN": 3,
      "SAN CAYETANO 1A SECCIÓN": 2,
      "SAN CAYETANO INFONAVIT": 1,
      "SAN ISIDRO": 2,
      "SAN ISIDRO INFONAVIT": 0,
      "SAN JUAN BOSCO": 1,
      "SAN JUAN DEL RÍO CENTRO": 0,
      "SAN PEDRO": 1,
      "SAN PEDRO AHUACATLAN": 1,
      "SANTA BÁRBARA LA CUEVA": 1,
      "SANTA CRUZ NIETO": 2,
      "SANTA LUCIA": 2,
      "SANTA ROSA XAJAY": 1,
      "SIN COLONIA DE REFERENCIA": 129,
      "VISTA": 3
    },
    "Indeterminado": {
      "ARCILA": 0,
      "BANTHI": 0,
      "BENITO JUÁREZ": 0,
      "BOSQUES DE BANTHI": 0,
      "CERRO GORDO": 0,
      "COMERI BANTHI": 0,
      "DEPORTIVA": 0,
      "DOLORES CUADRILLA DE ENMEDIO": 0,
      "DOLORES GODOY": 0,
      "EL CAZADERO": 0,
      "EL COTO": 0,
      "EL JAZMÍN": 0,
      "EL MARFIL": 0,
      "EL MIRADOR": 0,
      "EL PEDREGAL": 0,
      "EL PEDREGOSO INFONAVIT": 0,
      "GRANJAS BANTHI": 0,
      "JARDINES BANTHI": 0,
      "LA CRUZ": 0,
      "LA ESTANCIA": 0,
      "LA FLORESTA I": 0,
      "LA LLAVE": 0,
      "LA PEÑA": 0,
      "LA VALLA": 0,
      "LAS PALOMAS": 0,
      "LAS ÁGUILAS": 0,
      "LOMA LINDA": 0,
      "LOMAS DE SAN JUAN": 0,
      "LOMAS DEL PEDREGAL": 0,
      "LOS NOGALES": 0,
      "LOS OLIVOS": 0,
      "NUEVO SAN ISIDRO": 0,
      "NUEVO SAN JUAN": 0,
      "PALMA DE ROMERO": 0,
      "PALMILLAS": 0,
      "PASO DE MATA": 0,
      "PEDREGOSO COMEVI INDECO": 0,
      "PUERTA DE PALMILLAS": 0,
      "QUINTAS DE GUADALUPE": 0,
      "RANCHO BANTHI": 0,
      "RANCHO DE ENMEDIO": 0,
      "SABINO CHICO": 0,
      "SAGRADO CORAZÓN": 0,
      "SAN CAYETANO 1A SECCIÓN": 0,
      "SAN CAYETANO INFONAVIT": 0,
      "SAN ISIDRO": 0,
      "SAN ISIDRO INFONAVIT": 0,
      "SAN JUAN BOSCO": 0,
      "SAN JUAN DEL RÍO CENTRO": 0,
      "SAN PEDRO": 0,
      "SAN PEDRO AHUACATLAN": 0,
      "SANTA BÁRBARA LA CUEVA": 0,
      "SANTA CRUZ NIETO": 0,
      "SANTA LUCIA": 0,
      "SANTA ROSA XAJAY": 0,
      "SIN COLONIA DE REFERENCIA": 0,
      "VISTA": 0
    },
    "Mujeres": {
      "ARCILA": 0,
      "BANTHI": 2,
      "BENITO JUÁREZ": 0,
      "BOSQUES DE BANTHI": 2,
      "CERRO GORDO": 2,
      "COMERI BANTHI": 1,
      "DEPORTIVA": 0,
      "DOLORES CUADRILLA DE ENMEDIO": 1,
      "DOLORES GODOY": 0,
      "EL CAZADERO": 1,
      "EL COTO": 2,
      "EL JAZMÍN": 0,
      "EL MARFIL": 0,
      "EL MIRADOR": 0,
      "EL PEDREGAL": 0,
      "EL PEDREGOSO INFONAVIT": 0,
      "GRANJAS BANTHI": 6,
      "JARDINES BANTHI": 0,
      "LA CRUZ": 1,
      "LA ESTANCIA": 2,
      "LA FLORESTA I": 0,
      "LA LLAVE": 3,
      "LA PEÑA": 0,
      "LA VALLA": 3,
      "LAS PALOMAS": 0,
      "LAS ÁGUILAS": 3,
      "LOMA LINDA": 1,
      "LOMAS DE SAN JUAN": 2,
      "LOMAS DEL PEDREGAL": 1,
      "LOS NOGALES": 2,
      "LOS OLIVOS": 0,
      "NUEVO SAN ISIDRO": 0,
      "NUEVO SAN JUAN": 1,
      "PALMA DE ROMERO": 2,
      "PALMILLAS": 3,
      "PASO DE MATA": 2,
      "PEDREGOSO COMEVI INDECO": 0,
      "PUERTA DE PALMILLAS": 0,
      "QUINTAS DE GUADALUPE": 2,
      "RANCHO BANTHI": 1,
      "RANCHO DE ENMEDIO": 2,
      "SABINO CHICO": 1,
      "SAGRADO CORAZÓN": 1,
      "SAN CAYETANO 1A SECCIÓN": 2,
      "SAN CAYETANO INFONAVIT": 1,
      "SAN ISIDRO": 2,
      "SAN ISIDRO INFONAVIT": 1,
      "SAN JUAN BOSCO": 1,
      "SAN JUAN DEL RÍO CENTRO": 1,
      "SAN PEDRO": 0,
      "SAN PEDRO AHUACATLAN": 1,
      "SANTA BÁRBARA LA CUEVA": 0,
      "SANTA CRUZ NIETO": 0,
      "SANTA LUCIA": 0,
      "SANTA ROSA XAJAY": 0,
      "SIN COLONIA DE REFERENCIA": 116,
      "VISTA": 1
    }
  },
  "anual": {
    "Hombre": {
      "1.CIFRA SIN  AÑO DE REFERENCIA": 6,
      "1971": 1,
      "1981": 1,
      "1987": 1,
      "1998": 1,
      "2000": 1,
      "2004": 1,
      "2005": 1,
      "2007": 0,
      "2010": 1,
      "2011": 0,
      "2012": 8,
      "2013": 11,
      "2014": 15,
      "2015": 9,
      "2016": 9,
      "2017": 24,
      "2018": 10,
      "2019": 9,
      "2020": 13,
      "2021": 33,
      "2022": 18,
      "2023": 13,
      "2024": 11
    },
    "Indeterminado": {
      "1.CIFRA SIN  AÑO DE REFERENCIA": 0,
      "1971": 0,
      "1981": 0,
      "1987": 0,
      "1998": 0,
      "2000": 0,
      "2004": 0,
      "2005": 0,
      "2007": 0,
      "2010": 0,
      "2011": 0,
      "2012": 0,
      "2013": 0,
      "2014": 0,
      "2015": 0,
      "2016": 0,
      "2017": 0,
      "2018": 0,
      "2019": 0,
      "2020": 0,
      "2021": 0,
      "2022": 0,
      "2023": 0,
      "2024": 0
    },
    "Mujer": {
      "1.CIFRA SIN  AÑO DE REFERENCIA": 2,
      "1971": 0,
      "1981": 0,
      "1987": 0,
      "1998": 0,
      "2000": 0,
      "2004": 0,
      "2005": 1,
      "2007": 1,
      "2010": 1,
      "2011": 2,
      "2012": 20,
      "2013": 21,
      "2014": 16,
      "2015": 13,
      "2016": 10,
      "2017": 23,
      "2018": 8,
      "2019": 3,
      "2020": 4,
      "2021": 19,
      "2022": 21,
      "2023": 7,
      "2024": 4
    }
  },
  "mensual_ultimo_anio": {
    "Hombre": {
      "2023-ABRIL": 3,
      "2023-FEBRERO": 1,
      "2023-JUNIO": 2,
      "2023-MARZO": 3,
      "2023-MAYO": 1,
      "2023-NOVIEMBRE": 2,
      "2024-ABRIL": 0,
      "2024-ENERO": 3,
      "2024-FEBRERO": 1,
      "2024-JUNIO": 2,
      "2024-MARZO": 2,
      "2024-MAYO": 3
    },
    "Indeterminado": {
      "2023-ABRIL": 0,
      "2023-FEBRERO": 0,
      "2023-JUNIO": 0,
      "2023-MARZO": 0,
      "2023-MAYO": 0,
      "2023-NOVIEMBRE": 0,
      "2024-ABRIL": 0,
      "2024-ENERO": 0,
      "2024-FEBRERO": 0,
      "2024-JUNIO": 0,
      "2024-MARZO": 0,
      "2024-MAYO": 0
    },
    "Mujer": {
      "2023-ABRIL": 1,
      "2023-FEBRERO": 0,
      "2023-JUNIO": 1,
      "2023-MARZO": 2,
      "2023-MAYO": 0,
      "2023-NOVIEMBRE": 1,
      "2024-ABRIL": 1,
      "2024-ENERO": 0,
      "2024-FEBRERO": 0,
      "2024-JUNIO": 0,
      "2024-MARZO": 0,
      "2024-MAYO": 3
    }
  },
  "por_edad": {
    "Hombres": {
      "1": 5,
      "10": 3,
      "11": 0,
      "12": 1,
      "13": 4,
      "14": 9,
      "15": 3,
      "16": 4,
      "17": 8,
      "18": 5,
      "19": 1,
      "2": 2,
      "20": 4,
      "21": 5,
      "22": 10,
      "23": 3,
      "24": 2,
      "25": 7,
      "26": 6,
      "27": 8,
      "28": 5,
      "29": 4,
      "30": 2,
      "31": 2,
      "32": 6,
      "33": 3,
      "34": 5,
      "35": 0,
      "36": 6,
      "37": 3,
      "38": 3,
      "39": 4,
      "40": 4,
      "41": 3,
      "42": 2,
      "43": 4,
      "44": 4,
      "45": 5,
      "46": 3,
      "47": 4,
      "48": 1,
      "49": 2,
      "5": 3,
      "50": 3,
      "51": 1,
      "52": 2,
      "53": 2,
      "54": 1,
      "55": 1,
      "57": 1,
      "6": 1,
      "61": 2,
      "63": 2,
      "65": 2,
      "66": 1,
      "67": 1,
      "68": 2,
      "69": 2,
      "7": 0,
      "73": 1,
      "8": 0,
      "80": 1,
      "86": 2,
      "87": 1,
      "SIN EDAD DE REFERENCIA": 0
    },
    "Indeterminado": {
      "1": 0,
      "10": 0,
      "11": 0,
      "12": 0,
      "13": 0,
      "14": 0,
      "15": 0,
      "16": 0,
      "17": 0,
      "18": 0,
      "19": 0,
      "2": 0,
      "20": 0,
      "21": 0,
      "22": 0,
      "23": 0,
      "24": 0,
      "25": 0,
      "26": 0,
      "27": 0,
      "28": 0,
      "29": 0,
      "30": 0,
      "31": 0,
      "32": 0,
      "33": 0,
      "34": 0,
      "35": 0,
      "36": 0,
      "37": 0,
      "38": 0,
      "39": 0,
      "40": 0,
      "41": 0,
      "42": 0,
      "43": 0,
      "44": 0,
      "45": 0,
      "46": 0,
      "47": 0,
      "48": 0,
      "49": 0,
      "5": 0,
      "50": 0,
      "51": 0,
      "52": 0,
      "53": 0,
      "54": 0,
      "55": 0,
      "57": 0,
      "6": 0,
      "61": 0,
      "63": 0,
      "65": 0,
      "66": 0,
      "67": 0,
      "68": 0,
      "69": 0,
      "7": 0,
      "73": 0,
      "8": 0,
      "80": 0,
      "86": 0,
      "87": 0,
      "SIN EDAD DE REFERENCIA": 0
    },
    "Mujeres": {
      "1": 0,
      "10": 1,
      "11": 3,
      "12": 2,
      "13": 7,
      "14": 12,
      "15": 23,
      "16": 22,
      "17": 20,
      "18": 5,
      "19": 5,
      "2": 0,
      "20": 6,
      "21": 2,
      "22": 3,
      "23": 6,
      "24": 2,
      "25": 3,
      "26": 5,
      "27": 2,
      "28": 1,
      "29": 2,
      "30": 5,
      "31": 3,
      "32": 2,
      "33": 4,
      "34": 4,
      "35": 1,
      "36": 4,
      "37": 0,
      "38": 3,
      "39": 0,
      "40": 1,
      "41": 2,
      "42": 0,
      "43": 0,
      "44": 0,
      "45": 1,
      "46": 0,
      "47": 0,
      "48": 3,
      "49": 1,
      "5": 0,
      "50": 0,
      "51": 0,
      "52": 0,
      "53": 0,
      "54": 1,
      "55": 0,
      "57": 1,
      "6": 1,
      "61": 0,
      "63": 0,
      "65": 0,
      "66": 0,
      "67": 0,
      "68": 1,
      "69": 1,
      "7": 2,
      "73": 0,
      "8": 1,
      "80": 0,
      "86": 0,
      "87": 0,
      "SIN EDAD DE REFERENCIA": 2
    }
  },
  "por_nacionalidad": {
    "Hombres": {
      "MEXICANA": 197
    },
    "Indeterminado": {
      "MEXICANA": 0
    },
    "Mujeres": {
      "MEXICANA": 176
    }
  },
  "parametros": {
    "titulo": "PERSONAS DESAPARECIDAS, NO LOCALIZADAS Y LOCALIZADAS",
    "id_estatus_victima": "0",
    "fecha_inicio": "",
    "fecha_fin": "",
    "id_estado": "22",
    "id_municipio": "16",
    "mostrar_fecha_nula": "0",
    "id_colonia": "0",
    "id_nacionalidad": "0",
    "edad_inicio": "",
    "edad_fin": "",
    "mostrar_edad_nula": "0",
    "id_hipotesis": "",
    "id_medio_conocimiento": "",
    "id_circunstancia": "",
    "tiene_discapacidad": "",
    "id_tipo_discapacidad": "0",
    "id_etnia": "0",
    "id_lengua": "0",
    "id_religion": "",
    "es_migrante": "",
    "id_estatus_migratorio": "0",
    "es_lgbttti": "",
    "es_servidor_publico": "",
    "es_defensor_dh": "",
    "es_periodista": "",
    "es_sindicalista": "",
    "es_ong": "",
    "id_hipotesis_no_localizacion": "0",
    "id_delito": "0"
  }
}