{
  "totales": {
    "PorcentajeDesaparecidos": "87.23",
    "PorcentajeLocalizados": "12.77",
    "PorcentajeLocalizadosCV": "75.00",
    "PorcentajeLocalizadosSV": "25.00",
    "PorcentajeSoloDesaparecidos": "98.78",
    "PorcentajeSoloNoLocalizados": "1.22",
    "TotalDesaparecidos": "164",
    "TotalGlobal": "188",
    "TotalLocalizados": "24",
    "TotalLocalizadosCV": "18",
    "TotalLocalizadosSV": "06",
    "TotalSoloDesaparecidos": "162",
    "TotalSoloNoLocalizados": "02"
  },
  "espacial": {
    "Hombres": {
      "BURÓCRATA": 0,
      "DESIERTO DE SONORA": 3,
      "HOMBRES BLANCOS": 2,
      "MORELIA": 3,
      "PAPAGOS": 5,
      "SIN COLONIA DE REFERENCIA": 129,
      "SONOYTA CENTRO": 24
    },
    "Indeterminado": {
      "BURÓCRATA": 0,
      "DESIERTO DE SONORA": 0,
      "HOMBRES BLANCOS": 0,
      "MORELIA": 0,
      "PAPAGOS": 0,
      "SIN COLONIA DE REFERENCIA": 0,
      "SONOYTA CENTRO": 0
    },
    "Mujeres": {
      "BURÓCRATA": 1,
      "DESIERTO DE SONORA": 2,
      "HOMBRES BLANCOS": 0,
      "MORELIA": 1,
      "PAPAGOS": 0,
      "SIN COLONIA DE REFERENCIA": 14,
      "SONOYTA CENTRO": 4
    }
  },
  "anual": {
    "Hombre": {
      "1.CIFRA SIN  AÑO DE REFERENCIA": 6,
      "1999": 1,
      "2005": 1,
      "2006": 1,
      "2007": 1,
      "2008": 3,
      "2010": 2,
      "2011": 1,
      "2012": 8,
      "2013": 10,
      "2014": 17,
      "2015": 19,
      "2016": 9,
      "2017": 9,
      "2018": 18,
      "2019": 10,
      "2020": 14,
      "2021": 8,
      "2022": 8,
      "2023": 11,
      "2024": 9
    },
    "Indeterminado": {
      "1.CIFRA SIN  AÑO DE REFERENCIA": 0,
      "1999": 0,
      "2005": 0,
      "2006": 0,
      "2007": 0,
      "2008": 0,
      "2010": 0,
      "2011": 0,
      "2012": 0,
      "2013": 0,
      "2014": 0,
      "2015": 0,
      "2016": 0,
      "2017": 0,
      "2018": 0,
      "2019": 0,
      "2020": 0,
      "2021": 0,
      "2022": 0,
      "2023": 0,
      "2024": 0
    },
    "Mujer": {
      "1.CIFRA SIN  AÑO DE REFERENCIA": 0,
      "1999": 0,
      "2005": 0,
      "2006": 0,
      "2007": 0,
      "2008": 0,
      "2010": 1,
      "2011": 0,
      "2012": 1,
      "2013": 0,
      "2014": 0,
      "2015": 0,
      "2016": 3,
      "2017": 2,
      "2018": 4,
      "2019": 0,
      "2020": 3,
      "2021": 2,
      "2022": 0,
      "2023": 4,
      "2024": 2
    }
  },
  "mensual_ultimo_anio": {
    "Hombre": {
      "2023-ABRIL": 1,
      "2023-DICIEMBRE": 2,
      "2023-ENERO": 1,
      "2023-FEBRERO": 2,
      "2023-MARZO": 0,
      "2023-MAYO": 1,
      "2023-OCTUBRE": 0,
      "2023-SEPTIEMBRE": 4,
      "2024-ABRIL": 3,
      "2024-ENERO": 3,
      "2024-JUNIO": 1,
      "2024-MARZO": 2
    },
    "Indeterminado": {
      "2023-ABRIL": 0,
      "2023-DICIEMBRE": 0,
      "2023-ENERO": 0,
      "2023-FEBRERO": 0,
      "2023-MARZO": 0,
      "2023-MAYO": 0,
      "2023-OCTUBRE": 0,
      "2023-SEPTIEMBRE": 0,
      "2024-ABRIL": 0,
      "2024-ENERO": 0,
      "2024-JUNIO": 0,
      "2024-MARZO": 0
    },
    "Mujer": {
      "2023-ABRIL": 1,
      "2023-DICIEMBRE": 0,
      "2023-ENERO": 0,
      "2023-FEBRERO": 0,
      "2023-MARZO": 1,
      "2023-MAYO": 0,
      "2023-OCTUBRE": 1,
      "2023-SEPTIEMBRE": 1,
      "2024-ABRIL": 1,
      "2024-ENERO": 0,
      "2024-JUNIO": 1,
      "2024-MARZO": 0
    }
  },
  "por_edad": {
    "Hombres": {
      "13": 1,
      "15": 3,
      "16": 2,
      "17": 1,
      "18": 2,
      "19": 3,
      "20": 2,
      "21": 5,
      "22": 6,
      "23": 6,
      "24": 7,
      "25": 2,
      "26": 3,
      "27": 15,
      "28": 6,
      "29": 7,
      "3": 1,
      "30": 3,
      "31": 3,
      "32": 4,
      "33": 8,
      "34": 10,
      "35": 4,
      "36": 6,
      "37": 5,
      "38": 4,
      "39": 3,
      "40": 3,
      "41": 4,
      "43": 3,
      "44": 3,
      "46": 1,
      "47": 3,
      "48": 1,
      "49": 1,
      "50": 2,
      "51": 2,
      "52": 2,
      "53": 1,
      "54": 1,
      "55": 2,
      "61": 2,
      "62": 1,
      "67": 1,
      "80": 1,
      "SIN EDAD DE REFERENCIA": 10
    },
    "Indeterminado": {
      "13": 0,
      "15": 0,
      "16": 0,
      "17": 0,
      "18": 0,
      "19": 0,
      "20": 0,
      "21": 0,
      "22": 0,
      "23": 0,
      "24": 0,
      "25": 0,
      "26": 0,
      "27": 0,
      "28": 0,
      "29": 0,
      "3": 0,
      "30": 0,
      "31": 0,
      "32": 0,
      "33": 0,
      "34": 0,
      "35": 0,
      "36": 0,
      "37": 0,
      "38": 0,
      "39": 0,
      "40": 0,
      "41": 0,
      "43": 0,
      "44": 0,
      "46": 0,
      "47": 0,
      "48": 0,
      "49": 0,
      "50": 0,
      "51": 0,
      "52": 0,
      "53": 0,
      "54": 0,
      "55": 0,
      "61": 0,
      "62": 0,
      "67": 0,
      "80": 0,
      "SIN EDAD DE REFERENCIA": 0
    },
    "Mujeres": {
      "13": 0,
      "15": 3,
      "16": 0,
      "17": 0,
      "18": 1,
      "19": 0,
      "20": 1,
      "21": 0,
      "22": 1,
      "23": 0,
      "24": 2,
      "25": 0,
      "26": 0,
      "27": 0,
      "28": 0,
      "29": 1,
      "3": 0,
      "30": 1,
      "31": 1,
      "32": 0,
      "33": 0,
      "34": 0,
      "35": 0,
      "36": 1,
      "37": 0,
      "38": 0,
      "39": 0,
      "40": 1,
      "41": 0,
      "43": 0,
      "44": 0,
      "46": 1,
      "47": 0,
      "48": 0,
      "49": 0,
      "50": 1,
      "51": 0,
      "52": 0,
      "53": 1,
      "54": 0,
      "55": 0,
      "61": 0,
      "62": 0,
      "67": 0,
      "80": 0,
      "SIN EDAD DE REFERENCIA": 6
    }
  },
  "por_nacionalidad": {
    "Hombres": {
      "COLOMBIANA": 0,
      "ECUATORIANA": 1,
      "GUATEMALTECA": 4,
      "HONDUREÑA": 1,
      "MEXICANA": 108,
      "SE DESCONOCE": 52
    },
    "Indeterminado": {
      "COLOMBIANA": 0,
      "ECUATORIANA": 0,
      "GUATEMALTECA": 0,
      "HONDUREÑA": 0,
      "MEXICANA": 0,
      "SE DESCONOCE": 0
    },
    "Mujeres": {
      "COLOMBIANA": 1,
      "ECUATORIANA": 1,
      "GUATEMALTECA": 1,
      "HONDUREÑA": 0,
      "MEXICANA": 11,
      "SE DESCONOCE": 8
    }
  },
  "parametros": {
    "titulo": "PERSONAS DESAPARECIDAS, NO LOCALIZADAS Y LOCALIZADAS",
    "id_estatus_victima": "0",
    "fecha_inicio": "",
    "fecha_fin": "",
    "id_estado": "26",
    "id_municipio": "70",
    "mostrar_fecha_nula": "0",
    "id_colonia": "0",
    "id_nacionalidad": "0",
    "edad_inicio": "",
    "edad_fin": "",
    "mostrar_edad_nula": "0",
    "id_hipotesis": "",
    "id_medio_conocimiento": "",
    "id_circunstancia": "",
    "tiene_discapacidad": "",
    "id_tipo_discapacidad": "0",
    "id_etnia": "0",
    "id_lengua": "0",
    "id_religion": "",
    "es_migrante": "",
    "id_estatus_migratorio": "0",
    "es_lgbttti": "",
    "es_servidor_publico": "",
    "es_defensor_dh": "",
    "es_periodista": "",
    "es_sindicalista": "",
    "es_ong": "",
    "id_hipotesis_no_localizacion": "0",
    "id_delito": "0"
  }
}