{
  "totales": {
    "PorcentajeDesaparecidos": "35.79",
    "PorcentajeLocalizados": "64.21",
    "PorcentajeLocalizadosCV": "92.27",
    "PorcentajeLocalizadosSV": "7.73",
    "PorcentajeSoloDesaparecidos": "90.26",
    "PorcentajeSoloNoLocalizados": "9.74",
    "TotalDesaparecidos": "115956",
    "TotalGlobal": "324005",
    "TotalLocalizados": "208049",
    "TotalLocalizadosCV": "191968",
    "TotalLocalizadosSV": "16081",
    "TotalSoloDesaparecidos": "104658",
    "TotalSoloNoLocalizados": "11298"
  },
  "espacial": {
    "Hombre": {
      "AGUASCALIENTES": 2667,
      "BAJA CALIFORNIA": 3426,
      "BAJA CALIFORNIA SUR": 1631,
      "CAMPECHE": 649,
      "CHIAPAS": 3415,
      "CHIHUAHUA": 8860,
      "CIUDAD DE MEXICO": 9341,
      "COAHUILA": 3640,
      "COLIMA": 2401,
      "DURANGO": 2618,
      "ESTADO DE MEXICO": 26811,
      "GUANAJUATO": 8355,
      "GUERRERO": 4707,
      "HIDALGO": 2367,
      "JALISCO": 18494,
      "MICHOACAN ": 7641,
      "MORELOS": 3327,
      "NAYARIT": 2675,
      "NUEVO LEON": 12303,
      "OAXACA": 1789,
      "PUEBLA": 7560,
      "QUERETARO ": 1729,
      "QUINTANA ROO": 1721,
      "SAN LUIS POTOSI": 2628,
      "SE DESCONOCE": 700,
      "SINALOA": 10618,
      "SONORA": 5240,
      "TABASCO": 596,
      "TAMAULIPAS": 14719,
      "TLAXCALA": 750,
      "VERACRUZ ": 9389,
      "YUCATAN": 2734,
      "ZACATECAS": 5088
    },
    "Indeterminado": {
      "AGUASCALIENTES": 1,
      "BAJA CALIFORNIA": 6,
      "BAJA CALIFORNIA SUR": 4,
      "CAMPECHE": 1,
      "CHIAPAS": 1,
      "CHIHUAHUA": 4,
      "CIUDAD DE MEXICO": 312,
      "COAHUILA": 10,
      "COLIMA": 3,
      "DURANGO": 7,
      "ESTADO DE MEXICO": 20,
      "GUANAJUATO": 136,
      "GUERRERO": 17,
      "HIDALGO": 6,
      "JALISCO": 21,
      "MICHOACAN ": 9,
      "MORELOS": 5,
      "NAYARIT": 8,
      "NUEVO LEON": 4,
      "OAXACA": 7,
      "PUEBLA": 7,
      "QUERETARO ": 1,
      "QUINTANA ROO": 2,
      "SAN LUIS POTOSI": 4,
      "SE DESCONOCE": 104,
      "SINALOA": 5,
      "SONORA": 6,
      "TABASCO": 4,
      "TAMAULIPAS": 22,
      "TLAXCALA": 3,
      "VERACRUZ ": 37,
      "YUCATAN": 0,
      "ZACATECAS": 1
    },
    "Mujer": {
      "AGUASCALIENTES": 3250,
      "BAJA CALIFORNIA": 2289,
      "BAJA CALIFORNIA SUR": 834,
      "CAMPECHE": 860,
      "CHIAPAS": 3856,
      "CHIHUAHUA": 5177,
      "CIUDAD DE MEXICO": 7188,
      "COAHUILA": 1310,
      "COLIMA": 1878,
      "DURANGO": 1818,
      "ESTADO DE MEXICO": 29467,
      "GUANAJUATO": 8516,
      "GUERRERO": 1765,
      "HIDALGO": 2470,
      "JALISCO": 5545,
      "MICHOACAN ": 2912,
      "MORELOS": 2923,
      "NAYARIT": 1193,
      "NUEVO LEON": 8495,
      "OAXACA": 2365,
      "PUEBLA": 8206,
      "QUERETARO ": 1393,
      "QUINTANA ROO": 1654,
      "SAN LUIS POTOSI": 1859,
      "SE DESCONOCE": 317,
      "SINALOA": 3098,
      "SONORA": 2446,
      "TABASCO": 891,
      "TAMAULIPAS": 6544,
      "TLAXCALA": 893,
      "VERACRUZ ": 4959,
      "YUCATAN": 4300,
      "ZACATECAS": 1966
    }
  },
  "anual": {
    "Hombre": {
      "1.CIFRA SIN  AÑO DE REFERENCIA": 20582,
      "1952": 1,
      "1961": 0,
      "1962": 1,
      "1964": 2,
      "1965": 1,
      "1967": 4,
      "1968": 2,
      "1969": 7,
      "1970": 5,
      "1971": 18,
      "1972": 35,
      "1973": 44,
      "1974": 319,
      "1975": 69,
      "1976": 100,
      "1977": 123,
      "1978": 56,
      "1979": 21,
      "1980": 19,
      "1981": 33,
      "1982": 17,
      "1983": 10,
      "1984": 10,
      "1985": 14,
      "1986": 8,
      "1987": 17,
      "1988": 16,
      "1989": 24,
      "1990": 12,
      "1991": 15,
      "1992": 22,
      "1993": 25,
      "1994": 33,
      "1995": 26,
      "1996": 25,
      "1997": 33,
      "1998": 41,
      "1999": 43,
      "2000": 63,
      "2001": 81,
      "2002": 109,
      "2003": 110,
      "2004": 120,
      "2005": 176,
      "2006": 362,
      "2007": 1546,
      "2008": 1922,
      "2009": 2860,
      "2010": 5279,
      "2011": 6941,
      "2012": 6656,
      "2013": 9549,
      "2014": 9465,
      "2015": 7474,
      "2016": 8587,
      "2017": 10524,
      "2018": 10793,
      "2019": 15072,
      "2020": 14567,
      "2021": 15103,
      "2022": 14605,
      "2023": 17864,
      "2024": 8929
    },
    "Indeterminado": {
      "1.CIFRA SIN  AÑO DE REFERENCIA": 304,
      "1952": 0,
      "1961": 0,
      "1962": 0,
      "1964": 0,
      "1965": 0,
      "1967": 0,
      "1968": 0,
      "1969": 0,
      "1970": 0,
      "1971": 0,
      "1972": 0,
      "1973": 0,
      "1974": 4,
      "1975": 2,
      "1976": 3,
      "1977": 2,
      "1978": 2,
      "1979": 0,
      "1980": 0,
      "1981": 0,
      "1982": 0,
      "1983": 0,
      "1984": 0,
      "1985": 0,
      "1986": 0,
      "1987": 0,
      "1988": 0,
      "1989": 0,
      "1990": 0,
      "1991": 0,
      "1992": 0,
      "1993": 1,
      "1994": 0,
      "1995": 0,
      "1996": 0,
      "1997": 0,
      "1998": 0,
      "1999": 0,
      "2000": 0,
      "2001": 0,
      "2002": 0,
      "2003": 0,
      "2004": 0,
      "2005": 0,
      "2006": 0,
      "2007": 4,
      "2008": 0,
      "2009": 3,
      "2010": 1,
      "2011": 4,
      "2012": 5,
      "2013": 10,
      "2014": 11,
      "2015": 7,
      "2016": 11,
      "2017": 27,
      "2018": 68,
      "2019": 214,
      "2020": 23,
      "2021": 7,
      "2022": 26,
      "2023": 30,
      "2024": 9
    },
    "Mujer": {
      "1.CIFRA SIN  AÑO DE REFERENCIA": 18581,
      "1952": 0,
      "1961": 2,
      "1962": 0,
      "1964": 0,
      "1965": 0,
      "1967": 2,
      "1968": 1,
      "1969": 0,
      "1970": 0,
      "1971": 1,
      "1972": 7,
      "1973": 5,
      "1974": 20,
      "1975": 8,
      "1976": 14,
      "1977": 12,
      "1978": 14,
      "1979": 3,
      "1980": 2,
      "1981": 6,
      "1982": 2,
      "1983": 2,
      "1984": 0,
      "1985": 2,
      "1986": 1,
      "1987": 1,
      "1988": 3,
      "1989": 7,
      "1990": 2,
      "1991": 4,
      "1992": 10,
      "1993": 6,
      "1994": 8,
      "1995": 16,
      "1996": 13,
      "1997": 4,
      "1998": 10,
      "1999": 6,
      "2000": 17,
      "2001": 32,
      "2002": 56,
      "2003": 48,
      "2004": 48,
      "2005": 77,
      "2006": 250,
      "2007": 1455,
      "2008": 1314,
      "2009": 1953,
      "2010": 2258,
      "2011": 4087,
      "2012": 4273,
      "2013": 8211,
      "2014": 8555,
      "2015": 6379,
      "2016": 6566,
      "2017": 7057,
      "2018": 6719,
      "2019": 8985,
      "2020": 9483,
      "2021": 9318,
      "2022": 8885,
      "2023": 11767,
      "2024": 6069
    }
  },
  "mensual_ultimo_anio": {
    "Hombre": {
      "2023-AGOSTO": 1502,
      "2023-DICIEMBRE": 1289,
      "2023-NOVIEMBRE": 1361,
      "2023-OCTUBRE": 1524,
      "2023-SEPTIEMBRE": 1542,
      "2024-ABRIL": 1429,
      "2024-ENERO": 1400,
      "2024-FEBRERO": 1367,
      "2024-JULIO": 448,
      "2024-JUNIO": 1348,
      "2024-MARZO": 1483,
      "2024-MAYO": 1454
    },
    "Indeterminado": {
      "2023-AGOSTO": 1,
      "2023-DICIEMBRE": 0,
      "2023-NOVIEMBRE": 1,
      "2023-OCTUBRE": 3,
      "2023-SEPTIEMBRE": 1,
      "2024-ABRIL": 3,
      "2024-ENERO": 1,
      "2024-FEBRERO": 1,
      "2024-JULIO": 0,
      "2024-JUNIO": 0,
      "2024-MARZO": 2,
      "2024-MAYO": 2
    },
    "Mujer": {
      "2023-AGOSTO": 982,
      "2023-DICIEMBRE": 775,
      "2023-NOVIEMBRE": 939,
      "2023-OCTUBRE": 967,
      "2023-SEPTIEMBRE": 1011,
      "2024-ABRIL": 937,
      "2024-ENERO": 934,
      "2024-FEBRERO": 924,
      "2024-JULIO": 342,
      "2024-JUNIO": 850,
      "2024-MARZO": 1007,
      "2024-MAYO": 1075
    }
  },
  "por_edad": {
    "Hombres": {
      "0": 1473,
      "1": 940,
      "10": 930,
      "100": 2,
      "101": 3,
      "1013": 0,
      "1017": 0,
      "102": 1,
      "1026": 0,
      "103": 1,
      "1038": 1,
      "104": 3,
      "1046": 1,
      "1048": 1,
      "105": 3,
      "1052": 0,
      "106": 2,
      "108": 1,
      "109": 1,
      "11": 1121,
      "118": 1,
      "12": 1604,
      "121": 1,
      "122": 0,
      "123": 9,
      "124": 7,
      "127": 1,
      "13": 2753,
      "139": 1,
      "14": 3798,
      "15": 4771,
      "16": 5398,
      "17": 4974,
      "18": 4078,
      "1821": 1,
      "1822": 2,
      "1823": 0,
      "1824": 2,
      "1832": 1,
      "1874": 1,
      "19": 4072,
      "2": 969,
      "20": 4333,
      "2002": 1,
      "2014": 0,
      "2015": 1,
      "2018": 0,
      "21": 4680,
      "22": 4723,
      "23": 4936,
      "24": 4821,
      "25": 4826,
      "26": 4931,
      "27": 4852,
      "28": 4811,
      "29": 4494,
      "3": 896,
      "30": 4807,
      "31": 4303,
      "32": 4418,
      "33": 4282,
      "34": 3978,
      "35": 3929,
      "36": 3760,
      "37": 3709,
      "38": 3540,
      "39": 3219,
      "4": 884,
      "40": 3314,
      "41": 2900,
      "42": 3004,
      "43": 2761,
      "44": 2549,
      "45": 2569,
      "46": 2381,
      "47": 2314,
      "48": 2087,
      "49": 1885,
      "5": 773,
      "50": 1968,
      "51": 1601,
      "52": 1608,
      "53": 1455,
      "54": 1321,
      "55": 1252,
      "56": 1218,
      "57": 1015,
      "58": 1015,
      "59": 915,
      "6": 737,
      "60": 969,
      "61": 739,
      "62": 785,
      "63": 723,
      "639": 1,
      "64": 671,
      "65": 649,
      "66": 520,
      "67": 549,
      "68": 567,
      "69": 439,
      "7": 703,
      "70": 516,
      "71": 407,
      "72": 494,
      "73": 431,
      "74": 433,
      "75": 443,
      "76": 403,
      "77": 365,
      "78": 423,
      "79": 358,
      "8": 713,
      "80": 340,
      "81": 277,
      "82": 267,
      "826": 0,
      "828": 1,
      "83": 239,
      "84": 225,
      "85": 214,
      "86": 199,
      "87": 151,
      "88": 112,
      "89": 111,
      "9": 774,
      "90": 91,
      "91": 89,
      "912": 2,
      "92": 54,
      "93": 37,
      "94": 34,
      "95": 19,
      "952": 1,
      "96": 15,
      "962": 1,
      "97": 16,
      "98": 16,
      "99": 5,
      "SIN EDAD DE REFERENCIA": 8661
    },
    "Indeterminado": {
      "0": 4,
      "1": 2,
      "10": 2,
      "100": 0,
      "101": 0,
      "1013": 0,
      "1017": 0,
      "102": 0,
      "1026": 0,
      "103": 0,
      "1038": 0,
      "104": 0,
      "1046": 0,
      "1048": 0,
      "105": 0,
      "1052": 0,
      "106": 0,
      "108": 0,
      "109": 0,
      "11": 0,
      "118": 0,
      "12": 6,
      "121": 0,
      "122": 0,
      "123": 0,
      "124": 0,
      "127": 0,
      "13": 14,
      "139": 0,
      "14": 9,
      "15": 23,
      "16": 26,
      "17": 23,
      "18": 9,
      "1821": 0,
      "1822": 0,
      "1823": 0,
      "1824": 0,
      "1832": 0,
      "1874": 0,
      "19": 14,
      "2": 2,
      "20": 16,
      "2002": 0,
      "2014": 0,
      "2015": 0,
      "2018": 0,
      "21": 16,
      "22": 21,
      "23": 14,
      "24": 18,
      "25": 13,
      "26": 14,
      "27": 9,
      "28": 13,
      "29": 7,
      "3": 1,
      "30": 9,
      "31": 16,
      "32": 14,
      "33": 14,
      "34": 13,
      "35": 13,
      "36": 14,
      "37": 11,
      "38": 12,
      "39": 11,
      "4": 2,
      "40": 12,
      "41": 9,
      "42": 5,
      "43": 8,
      "44": 7,
      "45": 3,
      "46": 5,
      "47": 6,
      "48": 5,
      "49": 5,
      "5": 5,
      "50": 0,
      "51": 5,
      "52": 6,
      "53": 6,
      "54": 5,
      "55": 6,
      "56": 4,
      "57": 3,
      "58": 1,
      "59": 2,
      "6": 1,
      "60": 2,
      "61": 3,
      "62": 1,
      "63": 1,
      "639": 0,
      "64": 2,
      "65": 3,
      "66": 1,
      "67": 0,
      "68": 1,
      "69": 0,
      "7": 4,
      "70": 0,
      "71": 0,
      "72": 2,
      "73": 1,
      "74": 1,
      "75": 1,
      "76": 1,
      "77": 1,
      "78": 0,
      "79": 0,
      "8": 1,
      "80": 0,
      "81": 0,
      "82": 1,
      "826": 0,
      "828": 0,
      "83": 0,
      "84": 1,
      "85": 1,
      "86": 1,
      "87": 0,
      "88": 0,
      "89": 0,
      "9": 2,
      "90": 2,
      "91": 0,
      "912": 0,
      "92": 0,
      "93": 0,
      "94": 0,
      "95": 0,
      "952": 0,
      "96": 0,
      "962": 0,
      "97": 0,
      "98": 0,
      "99": 0,
      "SIN EDAD DE REFERENCIA": 243
    },
    "Mujeres": {
      "0": 1400,
      "1": 989,
      "10": 722,
      "100": 1,
      "101": 1,
      "1013": 1,
      "1017": 1,
      "102": 2,
      "1026": 1,
      "103": 0,
      "1038": 0,
      "104": 0,
      "1046": 0,
      "1048": 0,
      "105": 0,
      "1052": 1,
      "106": 0,
      "108": 0,
      "109": 0,
      "11": 1108,
      "118": 0,
      "12": 2959,
      "121": 0,
      "122": 1,
      "123": 9,
      "124": 5,
      "127": 0,
      "13": 7292,
      "139": 0,
      "14": 11685,
      "15": 14685,
      "16": 13537,
      "17": 10058,
      "18": 5223,
      "1821": 0,
      "1822": 0,
      "1823": 1,
      "1824": 2,
      "1832": 0,
      "1874": 0,
      "19": 3855,
      "2": 963,
      "20": 3216,
      "2002": 0,
      "2014": 1,
      "2015": 0,
      "2018": 1,
      "21": 3014,
      "22": 2834,
      "23": 2515,
      "24": 2419,
      "25": 2282,
      "26": 2139,
      "27": 1870,
      "28": 1832,
      "29": 1696,
      "3": 906,
      "30": 1687,
      "31": 1465,
      "32": 1390,
      "33": 1248,
      "34": 1190,
      "35": 1109,
      "36": 1060,
      "37": 975,
      "38": 937,
      "39": 876,
      "4": 822,
      "40": 836,
      "41": 682,
      "42": 784,
      "43": 632,
      "44": 611,
      "45": 580,
      "46": 567,
      "47": 512,
      "48": 464,
      "49": 431,
      "5": 809,
      "50": 408,
      "51": 353,
      "52": 307,
      "53": 284,
      "54": 296,
      "55": 289,
      "56": 244,
      "57": 222,
      "58": 237,
      "59": 202,
      "6": 727,
      "60": 220,
      "61": 152,
      "62": 178,
      "63": 184,
      "639": 0,
      "64": 137,
      "65": 156,
      "66": 141,
      "67": 145,
      "68": 123,
      "69": 119,
      "7": 706,
      "70": 129,
      "71": 112,
      "72": 118,
      "73": 116,
      "74": 98,
      "75": 118,
      "76": 112,
      "77": 99,
      "78": 101,
      "79": 85,
      "8": 717,
      "80": 96,
      "81": 68,
      "82": 81,
      "826": 1,
      "828": 0,
      "83": 70,
      "84": 71,
      "85": 62,
      "86": 60,
      "87": 58,
      "88": 32,
      "89": 32,
      "9": 677,
      "90": 24,
      "91": 15,
      "912": 0,
      "92": 15,
      "93": 16,
      "94": 14,
      "95": 9,
      "952": 0,
      "96": 4,
      "962": 0,
      "97": 5,
      "98": 4,
      "99": 7,
      "SIN EDAD DE REFERENCIA": 4861
    }
  },
  "por_nacionalidad": {
    "Hombres": {
      "AFGANA": 6,
      "ALBANESA": 1,
      "ALEMANA": 6,
      "ARGELINA": 0,
      "ARGENTINA": 22,
      "ARMENIO": 2,
      "AUSTRALIANA": 2,
      "AUSTRIACA": 1,
      "BANGLADESH": 2,
      "BELGA": 0,
      "BELICENA": 16,
      "BOLIVIANA": 3,
      "BRASILENA": 24,
      "BULGARA": 3,
      "CAMERUNEZA": 5,
      "CANADIENSE": 49,
      "CHILENA": 5,
      "CHINA": 8,
      "COLOMBIANA": 347,
      "COREANA (DEL SUR)": 2,
      "COREANA (REPUBLICA POPULAR)": 4,
      "COSTARRICENSE": 11,
      "CROATA": 2,
      "CUBANA": 152,
      "DANESA": 1,
      "DOMINICANA": 20,
      "ECUATORIANA": 69,
      "EGIPCIA": 3,
      "ESPANOLA": 23,
      "ESTADOS INDEPENDIENTES": 6,
      "ESTADOUNIDENSE": 778,
      "ESTONIO": 1,
      "ETIOPE": 1,
      "FILIPINA": 2,
      "FRANCESA": 8,
      "GANESA": 3,
      "GUATEMALTECA": 477,
      "HAITIANA": 16,
      "HINDU": 30,
      "HOLANDESA": 1,
      "HONDUREÑA": 590,
      "HUNGARA": 1,
      "INGLESA": 9,
      "IRANI": 4,
      "ISLANDESA": 2,
      "ISRAELI": 3,
      "ITALIANA": 15,
      "JAMAIQUINA": 5,
      "JAPONESA": 4,
      "JORDANA": 1,
      "KAMPUCHEANA": 0,
      "KUWAITI": 0,
      "LAOCIANA": 1,
      "LEICHTENSTEIN": 2,
      "LEONESA": 1,
      "LIBANESA": 2,
      "MALAYO": 9,
      "MALDIANA": 6,
      "MARROQUI": 14,
      "MEXICANA": 175055,
      "MOLDAVINA": 0,
      "MONEGASCA": 1,
      "NEOZELANDESA": 1,
      "NEPALESA": 1,
      "NICARAGUENSE": 161,
      "NIGERIANA": 1,
      "PANAMENA": 6,
      "PAQUISTANI": 1,
      "PARAGUAYA": 2,
      "PERUANA": 56,
      "POLACA": 5,
      "PUERTORRIQUENA": 2,
      "RUMANA": 0,
      "RUSA": 12,
      "SALVADORENA": 201,
      "SE DESCONOCE": 8711,
      "SIN NACIONALIDAD DE REFERENCIA": 3361,
      "SIRIA": 1,
      "SLOVAKO": 1,
      "SRI LANKA": 1,
      "SUDAFRICANA": 1,
      "SUECA": 1,
      "SUIZA": 3,
      "TUNEZINA": 2,
      "TURCA": 1,
      "UKRANIANA": 0,
      "URUGUAYA": 3,
      "VENEZOLANA": 218
    },
    "Indeterminado": {
      "AFGANA": 0,
      "ALBANESA": 0,
      "ALEMANA": 1,
      "ARGELINA": 0,
      "ARGENTINA": 0,
      "ARMENIO": 0,
      "AUSTRALIANA": 0,
      "AUSTRIACA": 0,
      "BANGLADESH": 0,
      "BELGA": 0,
      "BELICENA": 0,
      "BOLIVIANA": 0,
      "BRASILENA": 0,
      "BULGARA": 0,
      "CAMERUNEZA": 0,
      "CANADIENSE": 0,
      "CHILENA": 0,
      "CHINA": 0,
      "COLOMBIANA": 1,
      "COREANA (DEL SUR)": 0,
      "COREANA (REPUBLICA POPULAR)": 0,
      "COSTARRICENSE": 0,
      "CROATA": 0,
      "CUBANA": 8,
      "DANESA": 0,
      "DOMINICANA": 0,
      "ECUATORIANA": 23,
      "EGIPCIA": 0,
      "ESPANOLA": 0,
      "ESTADOS INDEPENDIENTES": 0,
      "ESTADOUNIDENSE": 1,
      "ESTONIO": 0,
      "ETIOPE": 0,
      "FILIPINA": 0,
      "FRANCESA": 0,
      "GANESA": 0,
      "GUATEMALTECA": 1,
      "HAITIANA": 0,
      "HINDU": 1,
      "HOLANDESA": 0,
      "HONDUREÑA": 1,
      "HUNGARA": 0,
      "INGLESA": 0,
      "IRANI": 0,
      "ISLANDESA": 0,
      "ISRAELI": 0,
      "ITALIANA": 0,
      "JAMAIQUINA": 0,
      "JAPONESA": 0,
      "JORDANA": 0,
      "KAMPUCHEANA": 0,
      "KUWAITI": 0,
      "LAOCIANA": 0,
      "LEICHTENSTEIN": 0,
      "LEONESA": 0,
      "LIBANESA": 0,
      "MALAYO": 0,
      "MALDIANA": 0,
      "MARROQUI": 0,
      "MEXICANA": 216,
      "MOLDAVINA": 0,
      "MONEGASCA": 0,
      "NEOZELANDESA": 0,
      "NEPALESA": 0,
      "NICARAGUENSE": 1,
      "NIGERIANA": 0,
      "PANAMENA": 0,
      "PAQUISTANI": 0,
      "PARAGUAYA": 0,
      "PERUANA": 0,
      "POLACA": 0,
      "PUERTORRIQUENA": 0,
      "RUMANA": 0,
      "RUSA": 0,
      "SALVADORENA": 1,
      "SE DESCONOCE": 521,
      "SIN NACIONALIDAD DE REFERENCIA": 0,
      "SIRIA": 0,
      "SLOVAKO": 0,
      "SRI LANKA": 0,
      "SUDAFRICANA": 0,
      "SUECA": 0,
      "SUIZA": 0,
      "TUNEZINA": 0,
      "TURCA": 0,
      "UKRANIANA": 0,
      "URUGUAYA": 0,
      "VENEZOLANA": 2
    },
    "Mujeres": {
      "AFGANA": 0,
      "ALBANESA": 0,
      "ALEMANA": 3,
      "ARGELINA": 1,
      "ARGENTINA": 6,
      "ARMENIO": 0,
      "AUSTRALIANA": 2,
      "AUSTRIACA": 0,
      "BANGLADESH": 0,
      "BELGA": 5,
      "BELICENA": 9,
      "BOLIVIANA": 3,
      "BRASILENA": 10,
      "BULGARA": 16,
      "CAMERUNEZA": 0,
      "CANADIENSE": 17,
      "CHILENA": 7,
      "CHINA": 2,
      "COLOMBIANA": 127,
      "COREANA (DEL SUR)": 1,
      "COREANA (REPUBLICA POPULAR)": 0,
      "COSTARRICENSE": 6,
      "CROATA": 0,
      "CUBANA": 73,
      "DANESA": 2,
      "DOMINICANA": 2,
      "ECUATORIANA": 43,
      "EGIPCIA": 2,
      "ESPANOLA": 6,
      "ESTADOS INDEPENDIENTES": 4,
      "ESTADOUNIDENSE": 654,
      "ESTONIO": 0,
      "ETIOPE": 0,
      "FILIPINA": 3,
      "FRANCESA": 3,
      "GANESA": 0,
      "GUATEMALTECA": 199,
      "HAITIANA": 6,
      "HINDU": 2,
      "HOLANDESA": 2,
      "HONDUREÑA": 271,
      "HUNGARA": 0,
      "INGLESA": 3,
      "IRANI": 0,
      "ISLANDESA": 0,
      "ISRAELI": 3,
      "ITALIANA": 9,
      "JAMAIQUINA": 2,
      "JAPONESA": 2,
      "JORDANA": 0,
      "KAMPUCHEANA": 1,
      "KUWAITI": 1,
      "LAOCIANA": 1,
      "LEICHTENSTEIN": 0,
      "LEONESA": 2,
      "LIBANESA": 0,
      "MALAYO": 6,
      "MALDIANA": 9,
      "MARROQUI": 7,
      "MEXICANA": 122858,
      "MOLDAVINA": 7,
      "MONEGASCA": 2,
      "NEOZELANDESA": 1,
      "NEPALESA": 0,
      "NICARAGUENSE": 69,
      "NIGERIANA": 0,
      "PANAMENA": 2,
      "PAQUISTANI": 0,
      "PARAGUAYA": 3,
      "PERUANA": 25,
      "POLACA": 3,
      "PUERTORRIQUENA": 0,
      "RUMANA": 2,
      "RUSA": 18,
      "SALVADORENA": 105,
      "SE DESCONOCE": 3600,
      "SIN NACIONALIDAD DE REFERENCIA": 4291,
      "SIRIA": 0,
      "SLOVAKO": 0,
      "SRI LANKA": 0,
      "SUDAFRICANA": 0,
      "SUECA": 1,
      "SUIZA": 1,
      "TUNEZINA": 0,
      "TURCA": 1,
      "UKRANIANA": 2,
      "URUGUAYA": 1,
      "VENEZOLANA": 112
    }
  },
  "parametros": {
    "titulo": "PERSONAS DESAPARECIDAS, NO LOCALIZADAS Y LOCALIZADAS",
    "id_estatus_victima": "0",
    "fecha_inicio": "",
    "fecha_fin": "",
    "id_estado": "0",
    "id_municipio": "0",
    "mostrar_fecha_nula": "0",
    "id_colonia": "0",
    "id_nacionalidad": "0",
    "edad_inicio": "",
    "edad_fin": "",
    "mostrar_edad_nula": "0",
    "id_hipotesis": "",
    "id_medio_conocimiento": "",
    "id_circunstancia": "",
    "tiene_discapacidad": "",
    "id_tipo_discapacidad": "0",
    "id_etnia": "0",
    "id_lengua": "0",
    "id_religion": "",
    "es_migrante": "",
    "id_estatus_migratorio": "0",
    "es_lgbttti": "",
    "es_servidor_publico": "",
    "es_defensor_dh": "",
    "es_periodista": "",
    "es_sindicalista": "",
    "es_ong": "",
    "id_hipotesis_no_localizacion": "0",
    "id_delito": "0"
  }
}